setup.py
django_scratchy.egg-info/PKG-INFO
django_scratchy.egg-info/SOURCES.txt
django_scratchy.egg-info/dependency_links.txt
django_scratchy.egg-info/requires.txt
django_scratchy.egg-info/top_level.txt
scratchy/__init__.py
scratchy/admin.py
scratchy/apps.py
scratchy/forms.py
scratchy/models.py
scratchy/tasks.py
scratchy/tests.py
scratchy/views.py
scratchy/management/__init__.py
scratchy/management/commands/__init__.py
scratchy/management/commands/execute_simple_spider.py
scratchy/management/commands/schedule_all_active_spiders.py
scratchy/migrations/0001_initial.py
scratchy/migrations/0002_spider_settings.py
scratchy/migrations/0003_auto_20200331_1848.py
scratchy/migrations/0004_auto_20200412_0950.py
scratchy/migrations/__init__.py