Metadata-Version: 1.1
Name: django-scratchy
Version: 0.3.0
Summary: Manage and run Scrapy spiders in Django
Home-page: https://github.com/jacoduplessis/scratchy
Author: Jaco du Plessis
Author-email: jaco@jacoduplessis.co.za
License: UNKNOWN
Keywords: django scrapy celery
Platform: UNKNOWN
Classifier: License :: OSI Approved :: MIT License
Classifier: Programming Language :: Python :: 3
